RGpdfconverter/__init__.py
RGpdfconverter/converter.py
RGpdfconverter/main.py
RGpdfconverter/common/Block.py
RGpdfconverter/common/Collection.py
RGpdfconverter/common/Element.py
RGpdfconverter/common/__init__.py
RGpdfconverter/common/constants.py
RGpdfconverter/common/docx.py
RGpdfconverter/common/share.py
RGpdfconverter/font/Fonts.py
RGpdfconverter/font/__init__.py
RGpdfconverter/image/Image.py
RGpdfconverter/image/ImageBlock.py
RGpdfconverter/image/ImageSpan.py
RGpdfconverter/image/ImagesExtractor.py
RGpdfconverter/image/__init__.py
RGpdfconverter/layout/Blocks.py
RGpdfconverter/layout/Column.py
RGpdfconverter/layout/Layout.py
RGpdfconverter/layout/Section.py
RGpdfconverter/layout/Sections.py
RGpdfconverter/layout/__init__.py
RGpdfconverter/page/BasePage.py
RGpdfconverter/page/Page.py
RGpdfconverter/page/Pages.py
RGpdfconverter/page/RawPage.py
RGpdfconverter/page/__init__.py
RGpdfconverter/shape/Path.py
RGpdfconverter/shape/Paths.py
RGpdfconverter/shape/Shape.py
RGpdfconverter/shape/Shapes.py
RGpdfconverter/shape/__init__.py
RGpdfconverter/table/Border.py
RGpdfconverter/table/Cell.py
RGpdfconverter/table/Cells.py
RGpdfconverter/table/Row.py
RGpdfconverter/table/Rows.py
RGpdfconverter/table/TableBlock.py
RGpdfconverter/table/TableStructure.py
RGpdfconverter/table/TablesConstructor.py
RGpdfconverter/table/__init__.py
RGpdfconverter/text/Char.py
RGpdfconverter/text/Line.py
RGpdfconverter/text/Lines.py
RGpdfconverter/text/Spans.py
RGpdfconverter/text/TextBlock.py
RGpdfconverter/text/TextSpan.py
RGpdfconverter/text/__init__.py
RGpdfconverter-0.3.dist-info/LICENSE
RGpdfconverter-0.3.dist-info/METADATA
RGpdfconverter-0.3.dist-info/WHEEL
RGpdfconverter-0.3.dist-info/entry_points.txt
RGpdfconverter-0.3.dist-info/top_level.txt
RGpdfconverter-0.3.dist-info/RECORD
